Metadata-Version: 2.1
Name: seed-otp
Version: 0.1.0
Summary: Python-based Bitcoin seed mnemonic one-time pad tool
Home-page: https://github.com/brndnmtthws/seed-otp
Author: Brenden Matthews
Author-email: brenden@diddyinc.com
License: UNKNOWN
Platform: UNKNOWN
Classifier: Programming Language :: Python :: 3
Classifier: License :: Public Domain
Classifier: Operating System :: OS Independent
Requires-Python: >=3.5
Provides-Extra: test
